{"nodes": [{"id": "deployment_\u7ec4\u7ec7\u67b6\u6784\u4e91\u7aef\u8865\u5e93\u6267\u884c\u8bf4\u660e", "label": "\u7ec4\u7ec7\u67b6\u6784\u4e91\u7aef\u8865\u5e93\u6267\u884c\u8bf4\u660e", "file_type": "document", "source_file": "deployment/\u7ec4\u7ec7\u67b6\u6784\u4e91\u7aef\u8865\u5e93\u6267\u884c\u8bf4\u660e-20260307.md", "source_location": null, "source_url": null, "captured_at": null, "author": null, "contributor": null}], "edges": [{"source": "deployment_\u7ec4\u7ec7\u67b6\u6784\u4e91\u7aef\u8865\u5e93\u6267\u884c\u8bf4\u660e", "target": "deployment_\u7d27\u6025\u54cd\u5e94\u624b\u518c", "relation": "references", "confidence": "EXTRACTED", "confidence_score": 1.0, "source_file": "deployment/\u7ec4\u7ec7\u67b6\u6784\u4e91\u7aef\u8865\u5e93\u6267\u884c\u8bf4\u660e-20260307.md", "source_location": null, "weight": 1.0}], "hyperedges": []}