{"nodes": [{"id": "bug_fix_prompt", "label": "Bug \u6392\u67e5\u4e0e\u4fee\u590d\u6a21\u677f", "file_type": "document", "source_file": ".github/prompts/bug-fix.prompt.md", "source_location": null, "source_url": null, "captured_at": null, "author": null, "contributor": null}], "edges": [{"source": "bug_fix_prompt", "target": "flyway", "relation": "references", "confidence": "EXTRACTED", "confidence_score": 1.0, "source_file": ".github/prompts/bug-fix.prompt.md", "source_location": null, "weight": 1.0}, {"source": "bug_fix_prompt", "target": "db_column_repair_runner", "relation": "references", "confidence": "EXTRACTED", "confidence_score": 1.0, "source_file": ".github/prompts/bug-fix.prompt.md", "source_location": null, "weight": 1.0}], "hyperedges": []}